jeeves_shell/__init__.py
jeeves_shell/cli.py
jeeves_shell/discover.py
jeeves_shell/entry_points.py
jeeves_shell/errors.py
jeeves_shell/import_by_path.py
jeeves_shell/jeeves.py
jeeves_shell-2.3.4.dist-info/METADATA
jeeves_shell-2.3.4.dist-info/WHEEL
jeeves_shell-2.3.4.dist-info/entry_points.txt
jeeves_shell-2.3.4.dist-info/RECORD
