Metadata-Version: 2.1
Name: jeeves-shell
Version: 2.3.4
Summary: Pythonic replacement for GNU Make
Home-page: https://github.com/jeeves-sh/jeeves-shell
License: MIT
Requires-Python: >=3.10,<4.0
Classifier: Development Status :: 3 - Alpha
Classifier: Intended Audience :: Developers
Classifier: License :: OSI Approved :: MIT License
Classifier: Operating System :: OS Independent
Classifier: Programming Language :: Python :: 3
Classifier: Programming Language :: Python :: 3.10
Classifier: Programming Language :: Python :: 3.11
Classifier: Programming Language :: Python :: 3.12
Classifier: Programming Language :: Python :: 3.13
Classifier: Topic :: Software Development :: Libraries :: Python Modules
Provides-Extra: all
Requires-Dist: documented (>=0.1.4)
Requires-Dist: funcy (>=2.0)
Requires-Dist: rich (>=13.3.5)
Requires-Dist: sh (>=2.0.4) ; extra == "all"
Requires-Dist: typer (>=0.12.4)
Project-URL: Repository, https://github.com/jeeves-sh/jeeves-shell
